python_byzatic_commons/__init__.py
python_byzatic_commons/crud/KeyValueCRUD.py
python_byzatic_commons/crud/__init__.py
python_byzatic_commons/crud/interfaces/KeyValueCRUDInterface.py
python_byzatic_commons/crud/interfaces/__init__.py
python_byzatic_commons/exceptions/BaseErrorException.py
python_byzatic_commons/exceptions/CriticalErrorException.py
python_byzatic_commons/exceptions/ExitHandlerException.py
python_byzatic_commons/exceptions/NotImplementedException.py
python_byzatic_commons/exceptions/OperationIncompleteException.py
python_byzatic_commons/exceptions/__init__.py
python_byzatic_commons/filereaders/ConfigParserFileReader.py
python_byzatic_commons/filereaders/JsonFileReader.py
python_byzatic_commons/filereaders/YamlFileReader.py
python_byzatic_commons/filereaders/__init__.py
python_byzatic_commons/filereaders/interfaces/BaseReaderInterface.py
python_byzatic_commons/filereaders/interfaces/__init__.py
python_byzatic_commons/flattener/__init__.py
python_byzatic_commons/flattener/config_parser_flattener/ConfigParserFlattener.py
python_byzatic_commons/flattener/config_parser_flattener/__init__.py
python_byzatic_commons/flattener/dictionary_flattener/DictionaryFlattener.py
python_byzatic_commons/flattener/dictionary_flattener/__init__.py
python_byzatic_commons/flattener/dl_flattener/DLFlattener.py
python_byzatic_commons/flattener/dl_flattener/__init__.py
python_byzatic_commons/flattener/interfaces/ConfigParserFlattenerInterface.py
python_byzatic_commons/flattener/interfaces/DLFlattenerInterface.py
python_byzatic_commons/flattener/interfaces/DictionaryFlattenerInterface.py
python_byzatic_commons/flattener/interfaces/FlattenerInterface.py
python_byzatic_commons/flattener/interfaces/JsonFlattenerInterface.py
python_byzatic_commons/flattener/interfaces/ListFlattenerInterface.py
python_byzatic_commons/flattener/interfaces/__init__.py
python_byzatic_commons/flattener/json_flattener/JsonFlattener.py
python_byzatic_commons/flattener/json_flattener/__init__.py
python_byzatic_commons-1.0.2.dist-info/licenses/LICENSE
python_byzatic_commons-1.0.2.dist-info/METADATA
python_byzatic_commons-1.0.2.dist-info/WHEEL
python_byzatic_commons-1.0.2.dist-info/top_level.txt
python_byzatic_commons-1.0.2.dist-info/RECORD
