Metadata-Version: 2.4
Name: python-byzatic-commons
Version: 1.0.2
Summary: A modular Python library with utilities for flattening, file parsing, error handling, and more.
Author-email: Svyatoslav Vlasov <s.vlasov.home@icloud.com>
License:                                  Apache License
Project-URL: Homepage, https://github.com/byzatic/PythonByzaticCommons
Requires-Python: >=3.8
License-File: LICENSE
Requires-Dist: pyyaml<7.0.0,>=6.0.0
Requires-Dist: configparser<6.0.0,>=5.0.0
Dynamic: license-file
